MANIFEST.in
README.rst
README.txt
setup.cfg
setup.py
docs/CREDITS.txt
docs/HISTORY.txt
docs/INSTALL.txt
docs/LICENSE.GPL
docs/LICENSE.txt
src/collective/__init__.py
src/collective.newsflash.egg-info/PKG-INFO
src/collective.newsflash.egg-info/SOURCES.txt
src/collective.newsflash.egg-info/dependency_links.txt
src/collective.newsflash.egg-info/entry_points.txt
src/collective.newsflash.egg-info/namespace_packages.txt
src/collective.newsflash.egg-info/not-zip-safe
src/collective.newsflash.egg-info/requires.txt
src/collective.newsflash.egg-info/top_level.txt
src/collective/newsflash/__init__.py
src/collective/newsflash/config.py
src/collective/newsflash/configure.zcml
src/collective/newsflash/controlpanel.py
src/collective/newsflash/interfaces.py
src/collective/newsflash/setuphandlers.py
src/collective/newsflash/testing.py
src/collective/newsflash/version.txt
src/collective/newsflash/Extensions/Install.py
src/collective/newsflash/Extensions/__init__.py
src/collective/newsflash/browser/__init__.py
src/collective/newsflash/browser/configure.zcml
src/collective/newsflash/browser/newsflash.py
src/collective/newsflash/browser/newsflash_viewlet.py
src/collective/newsflash/browser/javascript/jquery.ticker.js
src/collective/newsflash/browser/javascript/newsflash.js
src/collective/newsflash/browser/style/controls.png
src/collective/newsflash/browser/style/newsflash_icon.png
src/collective/newsflash/browser/style/ticker-style.css
src/collective/newsflash/browser/templates/htmllinks_viewlet.pt
src/collective/newsflash/browser/templates/newsflash_viewlet.pt
src/collective/newsflash/browser/templates/newsflash_viewlet_js.pt
src/collective/newsflash/locales/collective.newsflash.pot
src/collective/newsflash/locales/manual.pot
src/collective/newsflash/locales/plone.pot
src/collective/newsflash/locales/es/LC_MESSAGES/collective.newsflash.mo
src/collective/newsflash/locales/es/LC_MESSAGES/collective.newsflash.po
src/collective/newsflash/locales/es/LC_MESSAGES/plone.mo
src/collective/newsflash/locales/es/LC_MESSAGES/plone.po
src/collective/newsflash/locales/pt_BR/LC_MESSAGES/collective.newsflash.mo
src/collective/newsflash/locales/pt_BR/LC_MESSAGES/collective.newsflash.po
src/collective/newsflash/locales/pt_BR/LC_MESSAGES/plone.mo
src/collective/newsflash/locales/pt_BR/LC_MESSAGES/plone.po
src/collective/newsflash/portlet/__init__.py
